dicombrowser/__init__.py
dicombrowser/__main__.py
dicombrowser/_version.py
dicombrowser/dicom.py
dicombrowser/dicombrowser.py
dicombrowser/models.py
dicombrowser/resources_rc.py
dicombrowser-1.4.1.dist-info/LICENSE.txt
dicombrowser-1.4.1.dist-info/METADATA
dicombrowser-1.4.1.dist-info/WHEEL
dicombrowser-1.4.1.dist-info/entry_points.txt
dicombrowser-1.4.1.dist-info/top_level.txt
dicombrowser-1.4.1.dist-info/RECORD
