Metadata-Version: 2.1
Name: dicombrowser
Version: 1.4.1
Summary: Lightweight portable DICOM viewer with interface for images and tags
Home-page: http://github.com/ericspod/DicomBrowser
Author-email: Eric Kerfoot <eric.kerfoot@kcl.ac.uk>
License: GPLv3, see LICENSE.txt
Project-URL: homepage, http://github.com/ericspod/DicomBrowser
Platform: UNKNOWN
Requires-Python: >=3.7
License-File: LICENSE.txt
Requires-Dist: numpy
Requires-Dist: pyqt5
Requires-Dist: pyqtgraph
Requires-Dist: pydicom
Requires-Dist: pylibjpeg[all]
